surge/__init__.py
surge/surge.py
surge/test.py
surgetypes-0.1.1.dist-info/LICENSE
surgetypes-0.1.1.dist-info/METADATA
surgetypes-0.1.1.dist-info/WHEEL
surgetypes-0.1.1.dist-info/top_level.txt
surgetypes-0.1.1.dist-info/RECORD
