Metadata-Version: 2.1
Name: surgetypes
Version: 0.1.1
Summary: Automated type checking
Home-page: https://github.com/joshp-f/surgetypes-python
Author: Joshua p-f
Author-email: jporrittfraser@gmail.com
License: UNKNOWN
Platform: UNKNOWN
Classifier: Programming Language :: Python :: 3
Classifier: License :: OSI Approved :: MIT License
Classifier: Operating System :: OS Independent
Requires-Python: >=3.6
